Metadata-Version: 2.1
Name: pelican-micropub
Version: 0.1.0
Summary: A pelican plugin to read micropub entries in json form
Home-page: https://github.com/drivet/pelian-micropub
Author: Desmond Rivet
Author-email: desmond.rivet@gmail.com
License: GPLv3
Platform: UNKNOWN
Classifier: License :: OSI Approved :: GNU General Public License v3 (GPLv3)
Classifier: Programming Language :: Python
Classifier: Programming Language :: Python :: 3
Classifier: Programming Language :: Python :: 3.6
Classifier: Programming Language :: Python :: Implementation :: CPython
Classifier: Programming Language :: Python :: Implementation :: PyPy
Requires-Python: >=3.6.0
Provides-Extra: dev
